uv_upx/__init__.py
uv_upx/__main__.py
uv_upx/cli/__init__.py
uv_upx/cli/helpers/__init__.py
uv_upx/cli/helpers/main.py
uv_upx/cli/main.py
uv_upx/cli/upgrade/__init__.py
uv_upx/cli/upgrade/main.py
uv_upx/logging_custom/__init__.py
uv_upx/logging_custom/init_logging.py
uv_upx/main.py
uv_upx/py.typed
uv_upx/services/__init__.py
uv_upx/services/collect_dependencies/__init__.py
uv_upx/services/collect_dependencies/collect_groups_from_py_project.py
uv_upx/services/collect_dependencies/models.py
uv_upx/services/collect_top_level_dependencies/__init__.py
uv_upx/services/collect_top_level_dependencies/collect_top_level_dependencies.py
uv_upx/services/dependencies_from_project/__init__.py
uv_upx/services/dependencies_from_project/get_dependencies_from_project.py
uv_upx/services/dependencies_from_project/models.py
uv_upx/services/dependencies_from_project/parse_from_uv_lock.py
uv_upx/services/dependencies_from_project/parse_from_uv_lock_file.py
uv_upx/services/dependency_up/__init__.py
uv_upx/services/dependency_up/constants/__init__.py
uv_upx/services/dependency_up/constants/operators.py
uv_upx/services/dependency_up/handle_groups.py
uv_upx/services/dependency_up/models/__init__.py
uv_upx/services/dependency_up/models/changes_list.py
uv_upx/services/dependency_up/models/dependencies_list.py
uv_upx/services/dependency_up/models/dependency_parsed.py
uv_upx/services/dependency_up/models/included_dependency_group.py
uv_upx/services/dependency_up/parse_dependency.py
uv_upx/services/dependency_up/tests/__init__.py
uv_upx/services/dependency_up/tests/test_parse_dependency.py
uv_upx/services/dependency_up/tests/test_version_constraints.py
uv_upx/services/dependency_up/update_dependency.py
uv_upx/services/get_all_pyprojects/__init__.py
uv_upx/services/get_all_pyprojects/get_all_pyprojects.py
uv_upx/services/get_all_pyprojects/get_pyproject_paths_by_globs.py
uv_upx/services/get_all_pyprojects/models.py
uv_upx/services/normalize_paths/__init__.py
uv_upx-0.4.2.dist-info/WHEEL
uv_upx-0.4.2.dist-info/entry_points.txt
uv_upx-0.4.2.dist-info/METADATA
uv_upx-0.4.2.dist-info/RECORD
