Metadata-Version: 2.3
Name: uv-upx
Version: 0.4.2
Summary: Upgrade versions of dependencies in pyproject.toml files in uv-managed projects.
Keywords: uv,upgrade,dependencies,pyproject.toml,automation,cli
Author: Alirex
Author-email: Alirex <alirex.prime@gmail.com>
Requires-Dist: pydantic>=2.12.5
Requires-Dist: tomlkit>=0.13.3
Requires-Dist: typer>=0.20.1
Requires-Dist: prompt-toolkit>=3.0.52
Requires-Python: >=3.14.2
Project-URL: Documentation, https://github.com/Alirex/uv_upgrade
Project-URL: Homepage, https://github.com/Alirex/uv_upgrade
Project-URL: Issues, https://github.com/Alirex/uv_upgrade/issues
Project-URL: Repository, https://github.com/Alirex/uv_upgrade
